{
  "data": [
    {
      "timestamp": 1762750800000,
      "open": 11.88,
      "high": 12.9,
      "low": 11.8717,
      "close": 12.74,
      "volume": 272293
    },
    {
      "timestamp": 1762837200000,
      "open": 12.73,
      "high": 13.76,
      "low": 12.47,
      "close": 13.4,
      "volume": 340881
    },
    {
      "timestamp": 1762923600000,
      "open": 13.4,
      "high": 14.69,
      "low": 13.3,
      "close": 14.2,
      "volume": 444644
    },
    {
      "timestamp": 1763010000000,
      "open": 14.45,
      "high": 14.45,
      "low": 11.34,
      "close": 11.35,
      "volume": 634477
    }
  ],
  "timestamp": 1763142067540,
  "ttl": 86400000
}