{
  "data": [
    {
      "timestamp": 1758772800000,
      "open": 78.43,
      "high": 78.56,
      "low": 74.34,
      "close": 75.13,
      "volume": 440079
    },
    {
      "timestamp": 1758859200000,
      "open": 76.5,
      "high": 77.4853,
      "low": 75.91,
      "close": 77.19,
      "volume": 125653
    },
    {
      "timestamp": 1759118400000,
      "open": 77.72,
      "high": 78.02,
      "low": 76.01,
      "close": 77.83,
      "volume": 145703
    },
    {
      "timestamp": 1759204800000,
      "open": 77.72,
      "high": 84.03,
      "low": 77.565,
      "close": 83.52,
      "volume": 680324
    },
    {
      "timestamp": 1759291200000,
      "open": 84.56,
      "high": 91.68,
      "low": 84.56,
      "close": 91.28,
      "volume": 470939
    },
    {
      "timestamp": 1759377600000,
      "open": 89.5,
      "high": 91.42,
      "low": 88.53,
      "close": 90.68,
      "volume": 379091
    },
    {
      "timestamp": 1759464000000,
      "open": 91.34,
      "high": 96.2297,
      "low": 91.185,
      "close": 93.7,
      "volume": 248309
    },
    {
      "timestamp": 1759723200000,
      "open": 93.93,
      "high": 94.1151,
      "low": 92.033,
      "close": 92.34,
      "volume": 162213
    },
    {
      "timestamp": 1759809600000,
      "open": 91.98,
      "high": 93.3399,
      "low": 90.68,
      "close": 92.4,
      "volume": 131917
    },
    {
      "timestamp": 1759896000000,
      "open": 93.76,
      "high": 93.78,
      "low": 92.21,
      "close": 92.98,
      "volume": 95447
    },
    {
      "timestamp": 1759982400000,
      "open": 93.6,
      "high": 94.4189,
      "low": 91.936,
      "close": 92.37,
      "volume": 89255
    },
    {
      "timestamp": 1760068800000,
      "open": 93.25,
      "high": 93.25,
      "low": 87.89,
      "close": 88.19,
      "volume": 249541
    },
    {
      "timestamp": 1760328000000,
      "open": 87.7,
      "high": 89.76,
      "low": 87.2,
      "close": 87.94,
      "volume": 128515
    },
    {
      "timestamp": 1760414400000,
      "open": 87,
      "high": 89.52,
      "low": 86.32,
      "close": 88.72,
      "volume": 147784
    },
    {
      "timestamp": 1760500800000,
      "open": 87.88,
      "high": 90.3382,
      "low": 86.92,
      "close": 88.97,
      "volume": 132131
    },
    {
      "timestamp": 1760587200000,
      "open": 89.64,
      "high": 90.97,
      "low": 88,
      "close": 88.55,
      "volume": 78179
    },
    {
      "timestamp": 1760673600000,
      "open": 87.1,
      "high": 90.4793,
      "low": 86.41,
      "close": 90.22,
      "volume": 112175
    },
    {
      "timestamp": 1760932800000,
      "open": 91.05,
      "high": 93.49,
      "low": 91,
      "close": 93.04,
      "volume": 107905
    },
    {
      "timestamp": 1761019200000,
      "open": 93.55,
      "high": 94.62,
      "low": 92.23,
      "close": 93.44,
      "volume": 70448
    },
    {
      "timestamp": 1761105600000,
      "open": 95.56,
      "high": 96.72,
      "low": 94.6,
      "close": 95.42,
      "volume": 121298
    },
    {
      "timestamp": 1761192000000,
      "open": 94.56,
      "high": 96.41,
      "low": 94.15,
      "close": 95.43,
      "volume": 76728
    },
    {
      "timestamp": 1761278400000,
      "open": 95.62,
      "high": 96.72,
      "low": 95.19,
      "close": 95.27,
      "volume": 59260
    },
    {
      "timestamp": 1761537600000,
      "open": 95.48,
      "high": 96.1,
      "low": 93.762,
      "close": 96.04,
      "volume": 56233
    },
    {
      "timestamp": 1761624000000,
      "open": 96.28,
      "high": 96.28,
      "low": 93.745,
      "close": 94.15,
      "volume": 208027
    },
    {
      "timestamp": 1761710400000,
      "open": 93.58,
      "high": 93.98,
      "low": 90.44,
      "close": 91.64,
      "volume": 168474
    },
    {
      "timestamp": 1761796800000,
      "open": 91.19,
      "high": 93.96,
      "low": 90.88,
      "close": 91.79,
      "volume": 72529
    },
    {
      "timestamp": 1761883200000,
      "open": 89.08,
      "high": 92.1,
      "low": 88.56,
      "close": 91.82,
      "volume": 67489
    },
    {
      "timestamp": 1762146000000,
      "open": 91.24,
      "high": 92.3444,
      "low": 88.99,
      "close": 91.87,
      "volume": 114175
    },
    {
      "timestamp": 1762232400000,
      "open": 90.58,
      "high": 93.9,
      "low": 90.58,
      "close": 92.98,
      "volume": 96257
    },
    {
      "timestamp": 1762318800000,
      "open": 92.45,
      "high": 95.38,
      "low": 92.385,
      "close": 94.34,
      "volume": 52703
    },
    {
      "timestamp": 1762405200000,
      "open": 93.48,
      "high": 95.06,
      "low": 92.6484,
      "close": 94.89,
      "volume": 82069
    },
    {
      "timestamp": 1762491600000,
      "open": 94.6,
      "high": 95.03,
      "low": 92.55,
      "close": 95.03,
      "volume": 73340
    },
    {
      "timestamp": 1762750800000,
      "open": 94.28,
      "high": 97.5,
      "low": 94.28,
      "close": 97.25,
      "volume": 93010
    },
    {
      "timestamp": 1762837200000,
      "open": 97.74,
      "high": 104.24,
      "low": 97.74,
      "close": 104.06,
      "volume": 136922
    },
    {
      "timestamp": 1762923600000,
      "open": 104.47,
      "high": 109.1446,
      "low": 104.4,
      "close": 108.35,
      "volume": 185856
    },
    {
      "timestamp": 1763010000000,
      "open": 106.7,
      "high": 112.0309,
      "low": 106.51,
      "close": 108.32,
      "volume": 236507
    }
  ],
  "timestamp": 1763137376042,
  "ttl": 86400000
}