{
  "data": [
    {
      "timestamp": 1758686400000,
      "open": 314.05,
      "high": 316.5773,
      "low": 311.665,
      "close": 313.42,
      "volume": 7310513
    },
    {
      "timestamp": 1758772800000,
      "open": 314.12,
      "high": 315.65,
      "low": 311.8,
      "close": 313.45,
      "volume": 7083198
    },
    {
      "timestamp": 1758859200000,
      "open": 314.9,
      "high": 317.81,
      "low": 313.704,
      "close": 316.06,
      "volume": 7258136
    },
    {
      "timestamp": 1759118400000,
      "open": 317.06,
      "high": 318.01,
      "low": 313.66,
      "close": 315.69,
      "volume": 6462442
    },
    {
      "timestamp": 1759204800000,
      "open": 316.25,
      "high": 317.41,
      "low": 310.11,
      "close": 315.43,
      "volume": 11823315
    },
    {
      "timestamp": 1759291200000,
      "open": 313.97,
      "high": 314.59,
      "low": 307.41,
      "close": 310.71,
      "volume": 9235211
    },
    {
      "timestamp": 1759377600000,
      "open": 310,
      "high": 310.56,
      "low": 306.14,
      "close": 307.55,
      "volume": 7599973
    },
    {
      "timestamp": 1759464000000,
      "open": 308.51,
      "high": 311.66,
      "low": 308.21,
      "close": 310.03,
      "volume": 6029854
    },
    {
      "timestamp": 1759723200000,
      "open": 310.18,
      "high": 311.7474,
      "low": 305.1301,
      "close": 309.18,
      "volume": 7214502
    },
    {
      "timestamp": 1759809600000,
      "open": 309.35,
      "high": 310.01,
      "low": 304.7,
      "close": 307.69,
      "volume": 8454217
    },
    {
      "timestamp": 1759896000000,
      "open": 308.21,
      "high": 308.7832,
      "low": 303.55,
      "close": 304.03,
      "volume": 6489883
    },
    {
      "timestamp": 1759982400000,
      "open": 305.05,
      "high": 308.035,
      "low": 303.3947,
      "close": 305.53,
      "volume": 7060332
    },
    {
      "timestamp": 1760068800000,
      "open": 305.66,
      "high": 310.47,
      "low": 300.81,
      "close": 300.89,
      "volume": 8597384
    },
    {
      "timestamp": 1760328000000,
      "open": 305.6,
      "high": 309.46,
      "low": 305.45,
      "close": 307.97,
      "volume": 10788680
    },
    {
      "timestamp": 1760414400000,
      "open": 305.84,
      "high": 307,
      "low": 294.21,
      "close": 302.08,
      "volume": 16178755
    },
    {
      "timestamp": 1760500800000,
      "open": 306.39,
      "high": 312.1199,
      "low": 305.44,
      "close": 305.69,
      "volume": 11354778
    },
    {
      "timestamp": 1760587200000,
      "open": 305.35,
      "high": 308.6799,
      "low": 297.07,
      "close": 298.54,
      "volume": 10549447
    },
    {
      "timestamp": 1760673600000,
      "open": 299.16,
      "high": 299.55,
      "low": 294.2,
      "close": 297.56,
      "volume": 10153454
    },
    {
      "timestamp": 1760932800000,
      "open": 298.5,
      "high": 303.69,
      "low": 298.1601,
      "close": 302.36,
      "volume": 6894943
    },
    {
      "timestamp": 1761019200000,
      "open": 301.66,
      "high": 304.05,
      "low": 297,
      "close": 297.09,
      "volume": 7372671
    },
    {
      "timestamp": 1761105600000,
      "open": 297.77,
      "high": 298.0599,
      "low": 290.5448,
      "close": 294.11,
      "volume": 8054115
    },
    {
      "timestamp": 1761192000000,
      "open": 294.38,
      "high": 296.3699,
      "low": 292.51,
      "close": 294.54,
      "volume": 5438810
    },
    {
      "timestamp": 1761278400000,
      "open": 296.08,
      "high": 302.6,
      "low": 295.45,
      "close": 300.44,
      "volume": 7228330
    },
    {
      "timestamp": 1761537600000,
      "open": 302.16,
      "high": 304.53,
      "low": 301.01,
      "close": 304.15,
      "volume": 5642222
    },
    {
      "timestamp": 1761624000000,
      "open": 304.86,
      "high": 307.9674,
      "low": 303.16,
      "close": 305.36,
      "volume": 6335993
    },
    {
      "timestamp": 1761710400000,
      "open": 303.51,
      "high": 308.245,
      "low": 303.01,
      "close": 305.51,
      "volume": 7520324
    },
    {
      "timestamp": 1761796800000,
      "open": 305.79,
      "high": 312.61,
      "low": 305.1,
      "close": 309.44,
      "volume": 7514556
    },
    {
      "timestamp": 1761883200000,
      "open": 308.54,
      "high": 312.87,
      "low": 307.25,
      "close": 311.12,
      "volume": 7721297
    },
    {
      "timestamp": 1762146000000,
      "open": 311,
      "high": 312.32,
      "low": 306.21,
      "close": 309.35,
      "volume": 7770040
    },
    {
      "timestamp": 1762232400000,
      "open": 306.71,
      "high": 312.22,
      "low": 305.1,
      "close": 309.25,
      "volume": 7085164
    },
    {
      "timestamp": 1762318800000,
      "open": 309.61,
      "high": 313.1,
      "low": 305.63,
      "close": 311.68,
      "volume": 6865198
    },
    {
      "timestamp": 1762405200000,
      "open": 310.99,
      "high": 314.84,
      "low": 310.26,
      "close": 313.42,
      "volume": 7206111
    },
    {
      "timestamp": 1762491600000,
      "open": 311.89,
      "high": 314.43,
      "low": 307.642,
      "close": 314.21,
      "volume": 7302347
    },
    {
      "timestamp": 1762750800000,
      "open": 315,
      "high": 319.555,
      "low": 314.21,
      "close": 316.89,
      "volume": 5787167
    },
    {
      "timestamp": 1762837200000,
      "open": 317.5,
      "high": 319.05,
      "low": 315.28,
      "close": 315.62,
      "volume": 5030216
    },
    {
      "timestamp": 1762923600000,
      "open": 316.26,
      "high": 322.25,
      "low": 316.21,
      "close": 320.41,
      "volume": 10578266
    }
  ],
  "timestamp": 1763062493449,
  "ttl": 86400000
}