{
  "data": [
    {
      "timestamp": 1762750800000,
      "open": 20.31,
      "high": 20.99,
      "low": 19.48,
      "close": 20.55,
      "volume": 1679487
    },
    {
      "timestamp": 1762837200000,
      "open": 20.02,
      "high": 20.27,
      "low": 19,
      "close": 20.095,
      "volume": 942611
    },
    {
      "timestamp": 1762923600000,
      "open": 20.49,
      "high": 20.8494,
      "low": 19.64,
      "close": 20.16,
      "volume": 1002545
    },
    {
      "timestamp": 1763010000000,
      "open": 20.08,
      "high": 20.34,
      "low": 17.71,
      "close": 17.96,
      "volume": 1345644
    }
  ],
  "timestamp": 1763143561834,
  "ttl": 86400000
}