{
  "data": [
    {
      "timestamp": 1758772800000,
      "open": 20.65,
      "high": 21.44,
      "low": 19.59,
      "close": 21.43,
      "volume": 12822899
    },
    {
      "timestamp": 1758859200000,
      "open": 22.91,
      "high": 24.6,
      "low": 22.26,
      "close": 23.76,
      "volume": 25861180
    },
    {
      "timestamp": 1759118400000,
      "open": 23.85,
      "high": 24.22,
      "low": 22.39,
      "close": 22.49,
      "volume": 11912531
    },
    {
      "timestamp": 1759204800000,
      "open": 22.82,
      "high": 23.45,
      "low": 22.75,
      "close": 23.26,
      "volume": 8459990
    },
    {
      "timestamp": 1759291200000,
      "open": 22.8,
      "high": 23.51,
      "low": 22.68,
      "close": 23.1,
      "volume": 3619343
    },
    {
      "timestamp": 1759377600000,
      "open": 23.45,
      "high": 23.45,
      "low": 22.48,
      "close": 22.89,
      "volume": 4062814
    },
    {
      "timestamp": 1759464000000,
      "open": 23.15,
      "high": 23.53,
      "low": 22.59,
      "close": 22.79,
      "volume": 4048136
    },
    {
      "timestamp": 1759723200000,
      "open": 23.1,
      "high": 23.555,
      "low": 22.78,
      "close": 23.17,
      "volume": 3165432
    },
    {
      "timestamp": 1759809600000,
      "open": 23.3,
      "high": 23.8,
      "low": 22.98,
      "close": 23.13,
      "volume": 3457204
    },
    {
      "timestamp": 1759896000000,
      "open": 23.46,
      "high": 24.77,
      "low": 23.21,
      "close": 23.88,
      "volume": 6470571
    },
    {
      "timestamp": 1759982400000,
      "open": 24.02,
      "high": 24.28,
      "low": 23.2,
      "close": 23.39,
      "volume": 4399029
    },
    {
      "timestamp": 1760068800000,
      "open": 23.48,
      "high": 23.76,
      "low": 22.891,
      "close": 23.12,
      "volume": 2984143
    },
    {
      "timestamp": 1760328000000,
      "open": 23.81,
      "high": 24.7,
      "low": 23.72,
      "close": 24.43,
      "volume": 4744506
    },
    {
      "timestamp": 1760414400000,
      "open": 23.79,
      "high": 24.97,
      "low": 23.74,
      "close": 24.85,
      "volume": 3475824
    },
    {
      "timestamp": 1760500800000,
      "open": 25.145,
      "high": 25.54,
      "low": 24.72,
      "close": 24.93,
      "volume": 4367223
    },
    {
      "timestamp": 1760587200000,
      "open": 25.16,
      "high": 25.5,
      "low": 24.44,
      "close": 24.45,
      "volume": 2547307
    },
    {
      "timestamp": 1760673600000,
      "open": 23.98,
      "high": 24.65,
      "low": 23.9001,
      "close": 24.17,
      "volume": 3484638
    },
    {
      "timestamp": 1760932800000,
      "open": 24.54,
      "high": 25.05,
      "low": 24.295,
      "close": 24.93,
      "volume": 3061444
    },
    {
      "timestamp": 1761019200000,
      "open": 24.75,
      "high": 25.11,
      "low": 24.025,
      "close": 24.08,
      "volume": 3154192
    },
    {
      "timestamp": 1761105600000,
      "open": 24,
      "high": 24.188,
      "low": 22.8,
      "close": 23.38,
      "volume": 3682548
    },
    {
      "timestamp": 1761192000000,
      "open": 23.48,
      "high": 24.09,
      "low": 23.45,
      "close": 24.04,
      "volume": 3214368
    },
    {
      "timestamp": 1761278400000,
      "open": 24.56,
      "high": 24.9795,
      "low": 24.36,
      "close": 24.8,
      "volume": 2511447
    },
    {
      "timestamp": 1761537600000,
      "open": 25.33,
      "high": 25.39,
      "low": 24.29,
      "close": 24.54,
      "volume": 3911948
    },
    {
      "timestamp": 1761624000000,
      "open": 26,
      "high": 26.12,
      "low": 24.74,
      "close": 25.19,
      "volume": 5966150
    },
    {
      "timestamp": 1761710400000,
      "open": 25.155,
      "high": 30.21,
      "low": 24.27,
      "close": 29.75,
      "volume": 12669661
    },
    {
      "timestamp": 1761796800000,
      "open": 29.695,
      "high": 30.277,
      "low": 28.86,
      "close": 29.03,
      "volume": 5582010
    },
    {
      "timestamp": 1761883200000,
      "open": 29.37,
      "high": 29.83,
      "low": 28.75,
      "close": 29.37,
      "volume": 6003157
    },
    {
      "timestamp": 1762146000000,
      "open": 29.56,
      "high": 29.76,
      "low": 29.01,
      "close": 29.41,
      "volume": 4593066
    },
    {
      "timestamp": 1762232400000,
      "open": 28.5,
      "high": 28.76,
      "low": 27.765,
      "close": 27.82,
      "volume": 3932390
    },
    {
      "timestamp": 1762318800000,
      "open": 28.31,
      "high": 28.81,
      "low": 27.85,
      "close": 28.55,
      "volume": 2959475
    },
    {
      "timestamp": 1762405200000,
      "open": 28.7,
      "high": 28.71,
      "low": 27.29,
      "close": 27.55,
      "volume": 4299018
    },
    {
      "timestamp": 1762491600000,
      "open": 27.27,
      "high": 27.46,
      "low": 26.385,
      "close": 27.45,
      "volume": 3814115
    },
    {
      "timestamp": 1762750800000,
      "open": 28.15,
      "high": 28.28,
      "low": 27.085,
      "close": 27.14,
      "volume": 2946533
    },
    {
      "timestamp": 1762837200000,
      "open": 27.05,
      "high": 27.105,
      "low": 26.52,
      "close": 26.83,
      "volume": 2625453
    },
    {
      "timestamp": 1762923600000,
      "open": 27.06,
      "high": 28,
      "low": 26.8,
      "close": 27.35,
      "volume": 4053481
    },
    {
      "timestamp": 1763010000000,
      "open": 26.83,
      "high": 27.115,
      "low": 24.01,
      "close": 24.02,
      "volume": 6074806
    }
  ],
  "timestamp": 1763142660310,
  "ttl": 86400000
}