{
  "data": [
    {
      "timestamp": 1762750800000,
      "open": 249.68,
      "high": 249.96,
      "low": 234.6,
      "close": 238.88,
      "volume": 9527193
    },
    {
      "timestamp": 1762837200000,
      "open": 236.455,
      "high": 239.24,
      "low": 230.55,
      "close": 231.35,
      "volume": 8340252
    },
    {
      "timestamp": 1762923600000,
      "open": 233.9,
      "high": 234.84,
      "low": 219.8,
      "close": 224.61,
      "volume": 10800098
    },
    {
      "timestamp": 1763010000000,
      "open": 223.8,
      "high": 226,
      "low": 207.03,
      "close": 208.54,
      "volume": 16474424
    }
  ],
  "timestamp": 1763140386610,
  "ttl": 86400000
}