{
  "data": [
    {
      "timestamp": 1762750800000,
      "open": 30.11,
      "high": 31.6,
      "low": 28.5,
      "close": 29.37,
      "volume": 43451583
    },
    {
      "timestamp": 1762837200000,
      "open": 28.8,
      "high": 30.02,
      "low": 27.5,
      "close": 28.99,
      "volume": 33158306
    },
    {
      "timestamp": 1762923600000,
      "open": 28.82,
      "high": 29.57,
      "low": 26.11,
      "close": 26.4,
      "volume": 38694096
    },
    {
      "timestamp": 1763010000000,
      "open": 25.48,
      "high": 25.5,
      "low": 22.94,
      "close": 23.39,
      "volume": 48612644
    }
  ],
  "timestamp": 1763142241413,
  "ttl": 86400000
}