{
  "data": [
    {
      "timestamp": 1758772800000,
      "open": 25.395,
      "high": 27.2097,
      "low": 25.3812,
      "close": 26.7,
      "volume": 23257259.3333
    },
    {
      "timestamp": 1758859200000,
      "open": 26.13,
      "high": 27.06,
      "low": 24.6,
      "close": 24.6,
      "volume": 26512560.6667
    },
    {
      "timestamp": 1759118400000,
      "open": 24.15,
      "high": 24.72,
      "low": 23.445,
      "close": 24.27,
      "volume": 15676519.3333
    },
    {
      "timestamp": 1759204800000,
      "open": 24.48,
      "high": 25.3995,
      "low": 24.09,
      "close": 24.15,
      "volume": 15287664.6667
    },
    {
      "timestamp": 1759291200000,
      "open": 24.3,
      "high": 24.57,
      "low": 22.23,
      "close": 22.56,
      "volume": 24751323.6667
    },
    {
      "timestamp": 1759377600000,
      "open": 21.45,
      "high": 24.87,
      "low": 21.45,
      "close": 24.84,
      "volume": 30083003.6667
    },
    {
      "timestamp": 1759464000000,
      "open": 24.06,
      "high": 27.0897,
      "low": 23.64,
      "close": 25.53,
      "volume": 27915737
    },
    {
      "timestamp": 1759723200000,
      "open": 24.27,
      "high": 24.75,
      "low": 22.77,
      "close": 22.77,
      "volume": 20256596.6667
    },
    {
      "timestamp": 1759809600000,
      "open": 23.34,
      "high": 24.9,
      "low": 22.86,
      "close": 24.81,
      "volume": 22573645.3333
    },
    {
      "timestamp": 1759896000000,
      "open": 24.33,
      "high": 25.7322,
      "low": 23.88,
      "close": 24.18,
      "volume": 17149959
    },
    {
      "timestamp": 1759982400000,
      "open": 24.96,
      "high": 25.5846,
      "low": 24.45,
      "close": 24.54,
      "volume": 15796042.3333
    },
    {
      "timestamp": 1760068800000,
      "open": 24.45,
      "high": 27.2697,
      "low": 23.7,
      "close": 27.09,
      "volume": 26508604
    },
    {
      "timestamp": 1760328000000,
      "open": 25.74,
      "high": 26.22,
      "low": 24,
      "close": 24.12,
      "volume": 20608543.3333
    },
    {
      "timestamp": 1760414400000,
      "open": 25.17,
      "high": 26.1264,
      "low": 24.3003,
      "close": 24.87,
      "volume": 17739747.3333
    },
    {
      "timestamp": 1760500800000,
      "open": 24.24,
      "high": 25.2,
      "low": 23.58,
      "close": 24.15,
      "volume": 14769993
    },
    {
      "timestamp": 1760587200000,
      "open": 24.21,
      "high": 25.7397,
      "low": 23.73,
      "close": 24.9,
      "volume": 16174745.3333
    },
    {
      "timestamp": 1760673600000,
      "open": 25.275,
      "high": 25.5,
      "low": 23.46,
      "close": 23.67,
      "volume": 20122449
    },
    {
      "timestamp": 1760932800000,
      "open": 23.25,
      "high": 23.58,
      "low": 22.59,
      "close": 22.83,
      "volume": 13014091
    },
    {
      "timestamp": 1761019200000,
      "open": 22.98,
      "high": 23.385,
      "low": 22.6448,
      "close": 23.31,
      "volume": 10320493
    },
    {
      "timestamp": 1761105600000,
      "open": 23.255,
      "high": 24.76,
      "low": 23.04,
      "close": 23.75,
      "volume": 28091832
    },
    {
      "timestamp": 1761192000000,
      "open": 25.76,
      "high": 26.425,
      "low": 22.6001,
      "close": 22.65,
      "volume": 33131858
    },
    {
      "timestamp": 1761278400000,
      "open": 22.85,
      "high": 24.54,
      "low": 22.3905,
      "close": 24.19,
      "volume": 19503700
    },
    {
      "timestamp": 1761537600000,
      "open": 23.52,
      "high": 23.63,
      "low": 21.28,
      "close": 22.1,
      "volume": 25341329
    },
    {
      "timestamp": 1761624000000,
      "open": 21.89,
      "high": 22.2,
      "low": 20.75,
      "close": 21.33,
      "volume": 25247795
    },
    {
      "timestamp": 1761710400000,
      "open": 21.14,
      "high": 22.0598,
      "low": 20.85,
      "close": 21.27,
      "volume": 14917698
    },
    {
      "timestamp": 1761796800000,
      "open": 22.21,
      "high": 23.2512,
      "low": 21.84,
      "close": 23.21,
      "volume": 14425326
    },
    {
      "timestamp": 1761883200000,
      "open": 22.53,
      "high": 22.8555,
      "low": 21.3801,
      "close": 21.51,
      "volume": 17834586
    },
    {
      "timestamp": 1762146000000,
      "open": 21.57,
      "high": 21.76,
      "low": 19.875,
      "close": 20.38,
      "volume": 18301991
    },
    {
      "timestamp": 1762232400000,
      "open": 21.61,
      "high": 22.53,
      "low": 21.11,
      "close": 22.49,
      "volume": 19383138
    },
    {
      "timestamp": 1762318800000,
      "open": 21.71,
      "high": 22.86,
      "low": 20.2808,
      "close": 20.69,
      "volume": 18857304
    },
    {
      "timestamp": 1762405200000,
      "open": 20.73,
      "high": 23.1,
      "low": 20.23,
      "close": 22.13,
      "volume": 25470785
    },
    {
      "timestamp": 1762491600000,
      "open": 22.95,
      "high": 24.5373,
      "low": 22.95,
      "close": 23.78,
      "volume": 22402584
    },
    {
      "timestamp": 1762750800000,
      "open": 22.715,
      "high": 23.3589,
      "low": 21.57,
      "close": 22.05,
      "volume": 19395542
    },
    {
      "timestamp": 1762837200000,
      "open": 22.62,
      "high": 23.34,
      "low": 22.3301,
      "close": 22.62,
      "volume": 11188172
    },
    {
      "timestamp": 1762923600000,
      "open": 22.36,
      "high": 23.96,
      "low": 22.35,
      "close": 23.54,
      "volume": 10633030
    },
    {
      "timestamp": 1763010000000,
      "open": 24.38,
      "high": 27.275,
      "low": 24.22,
      "close": 26.67,
      "volume": 19969648
    }
  ],
  "timestamp": 1763145530936,
  "ttl": 86400000
}